{
    "boxShadow": "{{appsmith.theme.boxShadow.appBoxShadow}}",
    "onSort": "{{SelectQuery.run()}}",
    "isVisibleDownload": true,
    "iconSVG": "/static/media/icon.db8a9cbd.svg",
    "topRow": 6,
    "isSortable": true,
    "onPageChange": "{{SelectQuery.run()}}",
    "type": "TABLE_WIDGET",
    "animateLoading": true,
    "dynamicBindingPathList": [
        {"key": "tableData"},
        {"key": "derivedColumns.customColumn1.buttonLabel"},
        {"key": "primaryColumns.customColumn1.buttonLabel"},
        {"key": "accentColor"},
        {"key": "borderRadius"},
        {"key": "boxShadow"},
        {"key": "primaryColumns.customColumn1.borderRadius"},
        {"key": "primaryColumns.id.computedValue"},
        {"key": "primaryColumns.gender.computedValue"},
        {"key": "primaryColumns.latitude.computedValue"},
        {"key": "primaryColumns.longitude.computedValue"},
        {"key": "primaryColumns.dob.computedValue"},
        {"key": "primaryColumns.phone.computedValue"},
        {"key": "primaryColumns.email.computedValue"},
        {"key": "primaryColumns.image.computedValue"},
        {"key": "primaryColumns.country.computedValue"},
        {"key": "primaryColumns.name.computedValue"},
        {"key": "primaryColumns.created_at.computedValue"},
        {"key": "primaryColumns.updated_at.computedValue"}
    ],
    "leftColumn": 0,
    "delimiter": ",",
    "accentColor": "{{appsmith.theme.colors.primaryColor}}",
    "isVisibleFilters": true,
    "isVisible": "true",
    "enableClientSideSearch": true,
    "version": 3,
    "totalRecordsCount": 0,
    "isLoading": false,
    "onSearchTextChanged": "{{SelectQuery.run()}}",
    "childStylesheet": {
        "button": {
            "boxShadow": "none",
            "borderRadius": "{{appsmith.theme.borderRadius.appBorderRadius}}",
            "buttonColor": "{{appsmith.theme.colors.primaryColor}}"
        },
        "iconButton": {
            "boxShadow": "none",
            "borderRadius": "{{appsmith.theme.borderRadius.appBorderRadius}}",
            "menuColor": "{{appsmith.theme.colors.primaryColor}}"
        },
        "menuButton": {
            "boxShadow": "none",
            "borderRadius": "{{appsmith.theme.borderRadius.appBorderRadius}}",
            "menuColor": "{{appsmith.theme.colors.primaryColor}}"
        }
    },
    "borderRadius": "{{appsmith.theme.borderRadius.appBorderRadius}}",
    "primaryColumnId": "id",
    "columnSizeMap": {
        "task": 245,
        "step": 62,
        "status": 75
    },
    "widgetName": "data_table",
    "defaultPageSize": 0,
    "columnOrder": [
        "id",
        "gender",
        "latitude",
        "longitude",
        "dob",
        "phone",
        "email",
        "image",
        "country",
        "name",
        "created_at",
        "updated_at",
        "customColumn1"
    ],
    "dynamicPropertyPathList": [{"key": "primaryColumns.customColumn1.borderRadius"}],
    "displayName": "Table",
    "bottomRow": 85,
    "parentRowSpace": 10,
    "defaultSelectedRow": "0",
    "hideCard": false,
    "parentColumnSpace": 16.3125,
    "dynamicTriggerPathList": [
        {"key": "primaryColumns.customColumn1.onClick"},
        {"key": "onPageChange"},
        {"key": "onSearchTextChanged"},
        {"key": "onSort"}
    ],
    "primaryColumns": {
        "image": {
            "isCellVisible": true,
            "isDerived": false,
            "computedValue": "{{data_table.sanitizedTableData.map((currentRow) => ( currentRow.image))}}",
            "textSize": "0.875rem",
            "index": 7,
            "isVisible": true,
            "label": "image",
            "textColor": "",
            "columnType": "text",
            "horizontalAlignment": "LEFT",
            "width": 150,
            "enableFilter": true,
            "enableSort": true,
            "id": "image",
            "isDisabled": false,
            "cellBackground": "",
            "verticalAlignment": "CENTER"
        },
        "country": {
            "isCellVisible": true,
            "isDerived": false,
            "computedValue": "{{data_table.sanitizedTableData.map((currentRow) => ( currentRow.country))}}",
            "textSize": "0.875rem",
            "index": 8,
            "isVisible": true,
            "label": "country",
            "textColor": "",
            "columnType": "text",
            "horizontalAlignment": "LEFT",
            "width": 150,
            "enableFilter": true,
            "enableSort": true,
            "id": "country",
            "isDisabled": false,
            "cellBackground": "",
            "verticalAlignment": "CENTER"
        },
        "gender": {
            "isCellVisible": true,
            "isDerived": false,
            "computedValue": "{{data_table.sanitizedTableData.map((currentRow) => ( currentRow.gender))}}",
            "textSize": "0.875rem",
            "index": 1,
            "isVisible": true,
            "label": "gender",
            "textColor": "",
            "columnType": "text",
            "horizontalAlignment": "LEFT",
            "width": 150,
            "enableFilter": true,
            "enableSort": true,
            "id": "gender",
            "isDisabled": false,
            "cellBackground": "",
            "verticalAlignment": "CENTER"
        },
        "latitude": {
            "isCellVisible": true,
            "isDerived": false,
            "computedValue": "{{data_table.sanitizedTableData.map((currentRow) => ( currentRow.latitude))}}",
            "textSize": "0.875rem",
            "index": 2,
            "isVisible": true,
            "label": "latitude",
            "textColor": "",
            "columnType": "text",
            "horizontalAlignment": "LEFT",
            "width": 150,
            "enableFilter": true,
            "enableSort": true,
            "id": "latitude",
            "isDisabled": false,
            "cellBackground": "",
            "verticalAlignment": "CENTER"
        },
        "created_at": {
            "isCellVisible": true,
            "isDerived": false,
            "computedValue": "{{data_table.sanitizedTableData.map((currentRow) => ( currentRow.created_at))}}",
            "textSize": "0.875rem",
            "index": 10,
            "isVisible": true,
            "label": "created_at",
            "textColor": "",
            "columnType": "text",
            "horizontalAlignment": "LEFT",
            "width": 150,
            "enableFilter": true,
            "enableSort": true,
            "id": "created_at",
            "isDisabled": false,
            "cellBackground": "",
            "verticalAlignment": "CENTER"
        },
        "customColumn1": {
            "isCellVisible": true,
            "boxShadow": "none",
            "isDerived": true,
            "computedValue": "",
            "onClick": "{{showModal('Delete_Modal')}}",
            "buttonColor": "#DD4B34",
            "buttonStyle": "rgb(3, 179, 101)",
            "index": 5,
            "isVisible": true,
            "label": "Delete",
            "labelColor": "#FFFFFF",
            "buttonLabel": "{{data_table.sanitizedTableData.map((currentRow) => ( 'Delete'))}}",
            "columnType": "button",
            "borderRadius": "{{data_table.sanitizedTableData.map((currentRow) => ( appsmith.theme.borderRadius.appBorderRadius))}}",
            "menuColor": "#03B365",
            "width": 150,
            "enableFilter": true,
            "enableSort": true,
            "id": "customColumn1",
            "isDisabled": false,
            "buttonLabelColor": "#FFFFFF"
        },
        "updated_at": {
            "isCellVisible": true,
            "isDerived": false,
            "computedValue": "{{data_table.sanitizedTableData.map((currentRow) => ( currentRow.updated_at))}}",
            "textSize": "0.875rem",
            "index": 11,
            "isVisible": true,
            "label": "updated_at",
            "textColor": "",
            "columnType": "text",
            "horizontalAlignment": "LEFT",
            "width": 150,
            "enableFilter": true,
            "enableSort": true,
            "id": "updated_at",
            "isDisabled": false,
            "cellBackground": "",
            "verticalAlignment": "CENTER"
        },
        "phone": {
            "isCellVisible": true,
            "isDerived": false,
            "computedValue": "{{data_table.sanitizedTableData.map((currentRow) => ( currentRow.phone))}}",
            "textSize": "0.875rem",
            "index": 5,
            "isVisible": true,
            "label": "phone",
            "textColor": "",
            "columnType": "text",
            "horizontalAlignment": "LEFT",
            "width": 150,
            "enableFilter": true,
            "enableSort": true,
            "id": "phone",
            "isDisabled": false,
            "cellBackground": "",
            "verticalAlignment": "CENTER"
        },
        "dob": {
            "isCellVisible": true,
            "isDerived": false,
            "computedValue": "{{data_table.sanitizedTableData.map((currentRow) => ( currentRow.dob))}}",
            "textSize": "0.875rem",
            "index": 4,
            "isVisible": true,
            "label": "dob",
            "textColor": "",
            "columnType": "text",
            "horizontalAlignment": "LEFT",
            "width": 150,
            "enableFilter": true,
            "enableSort": true,
            "id": "dob",
            "isDisabled": false,
            "cellBackground": "",
            "verticalAlignment": "CENTER"
        },
        "name": {
            "isCellVisible": true,
            "isDerived": false,
            "computedValue": "{{data_table.sanitizedTableData.map((currentRow) => ( currentRow.name))}}",
            "textSize": "0.875rem",
            "index": 9,
            "isVisible": true,
            "label": "name",
            "textColor": "",
            "columnType": "text",
            "horizontalAlignment": "LEFT",
            "width": 150,
            "enableFilter": true,
            "enableSort": true,
            "id": "name",
            "isDisabled": false,
            "cellBackground": "",
            "verticalAlignment": "CENTER"
        },
        "id": {
            "isCellVisible": true,
            "isDerived": false,
            "computedValue": "{{data_table.sanitizedTableData.map((currentRow) => ( currentRow.id))}}",
            "textSize": "0.875rem",
            "index": 0,
            "isVisible": true,
            "label": "id",
            "textColor": "",
            "columnType": "text",
            "horizontalAlignment": "LEFT",
            "width": 150,
            "enableFilter": true,
            "enableSort": true,
            "id": "id",
            "isDisabled": false,
            "cellBackground": "",
            "verticalAlignment": "CENTER"
        },
        "email": {
            "isCellVisible": true,
            "isDerived": false,
            "computedValue": "{{data_table.sanitizedTableData.map((currentRow) => ( currentRow.email))}}",
            "textSize": "0.875rem",
            "index": 6,
            "isVisible": true,
            "label": "email",
            "textColor": "",
            "columnType": "text",
            "horizontalAlignment": "LEFT",
            "width": 150,
            "enableFilter": true,
            "enableSort": true,
            "id": "email",
            "isDisabled": false,
            "cellBackground": "",
            "verticalAlignment": "CENTER"
        },
        "longitude": {
            "isCellVisible": true,
            "isDerived": false,
            "computedValue": "{{data_table.sanitizedTableData.map((currentRow) => ( currentRow.longitude))}}",
            "textSize": "0.875rem",
            "index": 3,
            "isVisible": true,
            "label": "longitude",
            "textColor": "",
            "columnType": "text",
            "horizontalAlignment": "LEFT",
            "width": 150,
            "enableFilter": true,
            "enableSort": true,
            "id": "longitude",
            "isDisabled": false,
            "cellBackground": "",
            "verticalAlignment": "CENTER"
        }
    },
    "key": "zba5qel0au",
    "derivedColumns": {"customColumn1": {
        "isCellVisible": true,
        "boxShadow": "none",
        "isDerived": true,
        "computedValue": "",
        "onClick": "{{showModal('Delete_Modal')}}",
        "buttonColor": "#DD4B34",
        "buttonStyle": "rgb(3, 179, 101)",
        "index": 5,
        "isVisible": true,
        "label": "Delete",
        "labelColor": "#FFFFFF",
        "buttonLabel": "{{data_table.sanitizedTableData.map((currentRow) => ( 'Delete'))}}",
        "columnType": "button",
        "borderRadius": "0px",
        "menuColor": "#03B365",
        "width": 150,
        "enableFilter": true,
        "enableSort": true,
        "id": "customColumn1",
        "isDisabled": false,
        "buttonLabelColor": "#FFFFFF"
    }},
    "labelTextSize": "0.875rem",
    "rightColumn": 64,
    "textSize": "0.875rem",
    "widgetId": "hpy3pb4xft",
    "tableData": "{{SelectQuery.data}}",
    "label": "Data",
    "searchKey": "",
    "parentId": "59rw5mx0bq",
    "serverSidePaginationEnabled": true,
    "renderMode": "CANVAS",
    "horizontalAlignment": "LEFT",
    "isVisibleSearch": true,
    "isVisiblePagination": true,
    "verticalAlignment": "CENTER"
}